<?xml version="1.0" encoding="UTF-8"?>
<scenario>
    <world>
        <region name="EU-12">
            <ghgpolicy name="GHG">
                <market>Global</market>
                <constraint year="2020">47803.860754286</constraint>
                <constraint year="2025">50778.8358057396</constraint>
                <constraint year="2030">54148.8746037344</constraint>
                <constraint year="2035">54193.6994319812</constraint>
                <constraint year="2040">53772.103850834</constraint>
                <constraint year="2045">52913.3998681794</constraint>
                <constraint year="2050">51589.1194398273</constraint>
                <constraint year="2055">49995.5018082203</constraint>
                <constraint year="2060">48376.0630922114</constraint>
                <constraint year="2065">46706.9675149992</constraint>
                <constraint year="2070">44943.1210593414</constraint>
                <constraint year="2075">43062.6387283101</constraint>
                <constraint year="2080">41137.9829027134</constraint>
                <constraint year="2085">39166.602574213</constraint>
                <constraint year="2090">37202.3621518306</constraint>
                <constraint year="2095">35262.4725967633</constraint>
                <constraint year="2100">33339.0985385731</constraint>
            </ghgpolicy>
        </region>
        <region name="USA">
            <ghgpolicy name="GHG">
                <market>Global</market>
            </ghgpolicy>
        </region>
        <region name="Africa_Eastern">
            <ghgpolicy name="GHG">
                <market>Global</market>
            </ghgpolicy>
        </region>
        <region name="Africa_Northern">
            <ghgpolicy name="GHG">
                <market>Global</market>
            </ghgpolicy>
        </region>
        <region name="Africa_Southern">
            <ghgpolicy name="GHG">
                <market>Global</market>
            </ghgpolicy>
        </region>
        <region name="Africa_Western">
            <ghgpolicy name="GHG">
                <market>Global</market>
            </ghgpolicy>
        </region>
        <region name="Australia_NZ">
            <ghgpolicy name="GHG">
                <market>Global</market>
            </ghgpolicy>
        </region>
        <region name="Brazil">
            <ghgpolicy name="GHG">
                <market>Global</market>
            </ghgpolicy>
        </region>
        <region name="Canada">
            <ghgpolicy name="GHG">
                <market>Global</market>
            </ghgpolicy>
        </region>
        <region name="Central America and Caribbean">
            <ghgpolicy name="GHG">
                <market>Global</market>
            </ghgpolicy>
        </region>
        <region name="Central Asia">
            <ghgpolicy name="GHG">
                <market>Global</market>
            </ghgpolicy>
        </region>
        <region name="China">
            <ghgpolicy name="GHG">
                <market>Global</market>
            </ghgpolicy>
        </region>
        <region name="EU-15">
            <ghgpolicy name="GHG">
                <market>Global</market>
            </ghgpolicy>
        </region>
        <region name="Europe_Eastern">
            <ghgpolicy name="GHG">
                <market>Global</market>
            </ghgpolicy>
        </region>
        <region name="Europe_Non_EU">
            <ghgpolicy name="GHG">
                <market>Global</market>
            </ghgpolicy>
        </region>
        <region name="European Free Trade Association">
            <ghgpolicy name="GHG">
                <market>Global</market>
            </ghgpolicy>
        </region>
        <region name="India">
            <ghgpolicy name="GHG">
                <market>Global</market>
            </ghgpolicy>
        </region>
        <region name="Indonesia">
            <ghgpolicy name="GHG">
                <market>Global</market>
            </ghgpolicy>
        </region>
        <region name="Japan">
            <ghgpolicy name="GHG">
                <market>Global</market>
            </ghgpolicy>
        </region>
        <region name="Mexico">
            <ghgpolicy name="GHG">
                <market>Global</market>
            </ghgpolicy>
        </region>
        <region name="Middle East">
            <ghgpolicy name="GHG">
                <market>Global</market>
            </ghgpolicy>
        </region>
        <region name="Pakistan">
            <ghgpolicy name="GHG">
                <market>Global</market>
            </ghgpolicy>
        </region>
        <region name="Russia">
            <ghgpolicy name="GHG">
                <market>Global</market>
            </ghgpolicy>
        </region>
        <region name="South Africa">
            <ghgpolicy name="GHG">
                <market>Global</market>
            </ghgpolicy>
        </region>
        <region name="South America_Northern">
            <ghgpolicy name="GHG">
                <market>Global</market>
            </ghgpolicy>
        </region>
        <region name="South America_Southern">
            <ghgpolicy name="GHG">
                <market>Global</market>
            </ghgpolicy>
        </region>
        <region name="South Asia">
            <ghgpolicy name="GHG">
                <market>Global</market>
            </ghgpolicy>
        </region>
        <region name="South Korea">
            <ghgpolicy name="GHG">
                <market>Global</market>
            </ghgpolicy>
        </region>
        <region name="Southeast Asia">
            <ghgpolicy name="GHG">
                <market>Global</market>
            </ghgpolicy>
        </region>
        <region name="Taiwan">
            <ghgpolicy name="GHG">
                <market>Global</market>
            </ghgpolicy>
        </region>
        <region name="Argentina">
            <ghgpolicy name="GHG">
                <market>Global</market>
            </ghgpolicy>
        </region>
        <region name="Colombia">
            <ghgpolicy name="GHG">
                <market>Global</market>
            </ghgpolicy>
        </region>
    </world>
</scenario>
